keapi/__init__.py
keapi/_auth_mgr.py
keapi/_command_server.py
keapi/_error.py
keapi/_ke_var.py
keapi/_subscribe_server.py
keapi_robotics-1.0.0.dist-info/LICENSE
keapi_robotics-1.0.0.dist-info/METADATA
keapi_robotics-1.0.0.dist-info/WHEEL
keapi_robotics-1.0.0.dist-info/top_level.txt
keapi_robotics-1.0.0.dist-info/RECORD
