Metadata-Version: 2.1
Name: keapi-robotics
Version: 1.0.0
Summary: A API to communicate with a KEBA PLC via WebSockets
Author: Sebastian Redinger
Author-email: sebastian.redinger@fsbondtec.at
License: MIT
Keywords: keapi
Classifier: Development Status :: 4 - Beta
Classifier: License :: OSI Approved :: MIT License
Classifier: Programming Language :: Python :: 3
Classifier: Programming Language :: Python :: 3.8
Classifier: Programming Language :: Python :: 3.9
Classifier: Operating System :: MacOS :: MacOS X
Classifier: Operating System :: POSIX
Classifier: Operating System :: Microsoft :: Windows
Classifier: Topic :: Scientific/Engineering
Classifier: Intended Audience :: Developers
Requires-Python: >=3.8
License-File: LICENSE
Requires-Dist: websocket-client ==1.4.1
Provides-Extra: docs
Requires-Dist: Sphinx >=5.2 ; extra == 'docs'
Requires-Dist: sphinx-rtd-theme >=1.0 ; extra == 'docs'
